election/__init__.py
election/apps.py
election/conf.py
election/pagination.py
election/urls.py
election/admin/__init__.py
election/admin/candidate.py
election/admin/candidate_election.py
election/admin/election.py
election/admin/election_cycle.py
election/admin/election_day.py
election/admin/election_event.py
election/admin/election_type.py
election/admin/race.py
election/management/__init__.py
election/management/commands/__init__.py
election/management/commands/bootstrap_election.py
election/management/commands/bootstrap_election_events.py
election/management/commands/schedule_elections.py
election/migrations/0001_initial.py
election/migrations/0002_auto_20180109_1734.py
election/migrations/0003_electiontype_slug.py
election/migrations/0004_auto_20180206_2209.py
election/migrations/0005_auto_20180206_2238.py
election/migrations/0006_race_description.py
election/migrations/0007_electionevent.py
election/migrations/__init__.py
election/models/__init__.py
election/models/ballot_answer.py
election/models/ballot_measure.py
election/models/candidate.py
election/models/candidate_election.py
election/models/election.py
election/models/election_cycle.py
election/models/election_day.py
election/models/election_event.py
election/models/election_type.py
election/models/race.py
election/serializers/__init__.py
election/serializers/ballot_answer.py
election/serializers/ballot_measure.py
election/serializers/candidate.py
election/serializers/election.py
election/serializers/election_cycle.py
election/serializers/election_day.py
election/serializers/election_event.py
election/serializers/election_type.py
election/serializers/race.py
election/utils/__init__.py
election/utils/importers.py
election/viewsets/__init__.py
election/viewsets/ballot_answer.py
election/viewsets/ballot_measure.py
election/viewsets/base.py
election/viewsets/candidate.py
election/viewsets/election.py
election/viewsets/election_cycle.py
politico_civic_election-0.3.3.dist-info/METADATA
politico_civic_election-0.3.3.dist-info/RECORD
politico_civic_election-0.3.3.dist-info/WHEEL
politico_civic_election-0.3.3.dist-info/top_level.txt
